{
  "TranslationProperties": {
    "Name": "Leave map",
    "Description": "Right click to leave the current map."
  },
  "Icon": "Icons/ItemsGenerated/Red_Orb_Hyvexa.png",
  "Quality": "Developer",
  "Categories": [
    "Items.Ingredients"
  ],
  "Model": "Items/Custom/Orb Hyvexa.blockymodel",
  "Texture": "Items/Custom/Orb_Texture_red.png",
  "PlayerAnimationsId": "Block",
  "IconProperties": {
    "Scale": 0.9,
    "Rotation": [
      0,
      196,
      0
    ],
    "Translation": [
      0,
      -12
    ]
  },
  "ItemEntity": {
    "ParticleSystemId": null
  },
  "MaxStack": 1,
  "Scale": 1.6,
  "Light": {
    "Color": "#3d6"
  },
  "Particles": [
    {
      "Color": "#ff1111",
      "SystemId": "Temple_Light_Lantern"
    }
  ],
  "ItemSoundSetId": "ISS_Items_Gems",
  "DropOnDeath": true,
  "Interactions": {
    "Secondary": "Ingredient_Void_Essence"
  }
}
